sie_banxico/__init__.py
sie_banxico/sie_banxico.py
sie_banxico-0.0.1.dist-info/LICENCE.txt
sie_banxico-0.0.1.dist-info/METADATA
sie_banxico-0.0.1.dist-info/WHEEL
sie_banxico-0.0.1.dist-info/top_level.txt
sie_banxico-0.0.1.dist-info/RECORD
