Metadata-Version: 2.1
Name: sie-banxico
Version: 0.0.1
Summary: A python class for the Economic Information System (SIE) API of Banco de México.
Home-page: https://github.com/DillanAS/sie_banxico
Author: Dillan Aguirre Sedeño
Author-email: dillan.as22@gmail.com
License: UNKNOWN
Project-URL: Source, https://github.com/DillanAS/
Project-URL: Tracker, https://github.com/DillanAS/sie_banxico/issues
Project-URL: Connect with me!, https://www.linkedin.com/in/dillanas22/
Keywords: python,api,economic data,banxico,mexico
Platform: UNKNOWN
Classifier: Programming Language :: Python :: 3
Classifier: License :: OSI Approved :: MIT License
Classifier: Operating System :: OS Independent
Requires-Python: >=3.6
License-File: LICENCE.txt
